{"Icheck":{"minimumDiscordVersion":105112,"version":"1.0.0","build":"https://raw.githubusercontent.com/Alpha62579/aliucord-plugins/builds/%s.zip"},"AOUutilsHelper":{"minimumDiscordVersion":105112,"version":"1.0.0","build":"https://raw.githubusercontent.com/Alpha62579/aliucord-plugins/builds/%s.zip","changelog":"# 1.0.1\n* Trigger update because I wanted to see the updater in action. :>"},"AutoThonk":{"minimumDiscordVersion":105112,"version":"1.0.0","build":"https://raw.githubusercontent.com/Alpha62579/aliucord-plugins/builds/%s.zip"},"Rawify":{"minimumDiscordVersion":105112,"version":"1.0.0","build":"https://raw.githubusercontent.com/Alpha62579/aliucord-plugins/builds/%s.zip"}}